{"OrderID":10730,"CustomerID":"BONAP","OrderDate":"1997-11-05T00:00:00.000Z","LineItems":[{"ProductID":16,"UnitPrice":17.45,"Quantity":15,"Discount":0.05},{"ProductID":31,"UnitPrice":12.5,"Quantity":3,"Discount":0.05},{"ProductID":65,"UnitPrice":21.05,"Quantity":10,"Discount":0.05}]}
{"OrderID":10731,"CustomerID":"CHOPS","OrderDate":"1997-11-06T00:00:00.000Z","LineItems":[{"ProductID":21,"UnitPrice":10.0,"Quantity":40,"Discount":0.05},{"ProductID":51,"UnitPrice":53.0,"Quantity":30,"Discount":0.05}]}
{"OrderID":10732,"CustomerID":"BONAP","OrderDate":"1997-11-06T00:00:00.000Z","LineItems":[{"ProductID":76,"UnitPrice":18.0,"Quantity":20,"Discount":0.0}]}
{"OrderID":10733,"CustomerID":"BERGS","OrderDate":"1997-11-07T00:00:00.000Z","LineItems":[{"ProductID":14,"UnitPrice":23.25,"Quantity":16,"Discount":0.0},{"ProductID":28,"UnitPrice":45.6,"Quantity":20,"Discount":0.0},{"ProductID":52,"UnitPrice":7.0,"Quantity":25,"Discount":0.0}]}
