{"OrderID":11000,"CustomerID":"RATTC","OrderDate":"1998-04-06T00:00:00.000Z","LineItems":[{"ProductID":77,"UnitPrice":13.0,"Quantity":30,"Discount":0.0},{"ProductID":24,"UnitPrice":4.5,"Quantity":30,"Discount":0.25},{"ProductID":4,"UnitPrice":22.0,"Quantity":25,"Discount":0.25}]}
{"OrderID":11001,"CustomerID":"FOLKO","OrderDate":"1998-04-06T00:00:00.000Z","LineItems":[{"ProductID":46,"UnitPrice":12.0,"Quantity":25,"Discount":0.0},{"ProductID":7,"UnitPrice":30.0,"Quantity":60,"Discount":0.0},{"ProductID":22,"UnitPrice":21.0,"Quantity":25,"Discount":0.0},{"ProductID":55,"UnitPrice":24.0,"Quantity":6,"Discount":0.0}]}
{"OrderID":11002,"CustomerID":"SAVEA","OrderDate":"1998-04-06T00:00:00.000Z","LineItems":[{"ProductID":42,"UnitPrice":14.0,"Quantity":24,"Discount":0.15},{"ProductID":13,"UnitPrice":6.0,"Quantity":56,"Discount":0.0},{"ProductID":35,"UnitPrice":18.0,"Quantity":15,"Discount":0.15},{"ProductID":55,"UnitPrice":24.0,"Quantity":40,"Discount":0.0}]}
{"OrderID":11003,"CustomerID":"THECR","OrderDate":"1998-04-06T00:00:00.000Z","LineItems":[{"ProductID":40,"UnitPrice":18.4,"Quantity":10,"Discount":0.0},{"ProductID":52,"UnitPrice":7.0,"Quantity":10,"Discount":0.0},{"ProductID":1,"UnitPrice":18.0,"Quantity":4,"Discount":0.0}]}
