{"OrderID":10975,"CustomerID":"BOTTM","OrderDate":"1998-03-25T00:00:00.000Z","LineItems":[{"ProductID":8,"UnitPrice":40.0,"Quantity":16,"Discount":0.0},{"ProductID":75,"UnitPrice":7.75,"Quantity":10,"Discount":0.0}]}
{"OrderID":10976,"CustomerID":"HILAA","OrderDate":"1998-03-25T00:00:00.000Z","LineItems":[{"ProductID":28,"UnitPrice":45.6,"Quantity":20,"Discount":0.0}]}
{"OrderID":10977,"CustomerID":"FOLKO","OrderDate":"1998-03-26T00:00:00.000Z","LineItems":[{"ProductID":51,"UnitPrice":53.0,"Quantity":10,"Discount":0.0},{"ProductID":47,"UnitPrice":9.5,"Quantity":30,"Discount":0.0},{"ProductID":63,"UnitPrice":43.9,"Quantity":20,"Discount":0.0},{"ProductID":39,"UnitPrice":18.0,"Quantity":30,"Discount":0.0}]}
{"OrderID":10978,"CustomerID":"MAISD","OrderDate":"1998-03-26T00:00:00.000Z","LineItems":[{"ProductID":21,"UnitPrice":10.0,"Quantity":40,"Discount":0.15},{"ProductID":40,"UnitPrice":18.4,"Quantity":10,"Discount":0.0},{"ProductID":44,"UnitPrice":19.45,"Quantity":6,"Discount":0.15},{"ProductID":8,"UnitPrice":40.0,"Quantity":20,"Discount":0.15}]}
