{"OrderID":11012,"CustomerID":"FRANK","OrderDate":"1998-04-09T00:00:00.000Z","LineItems":[{"ProductID":60,"UnitPrice":34.0,"Quantity":36,"Discount":0.05},{"ProductID":19,"UnitPrice":9.2,"Quantity":50,"Discount":0.05},{"ProductID":71,"UnitPrice":21.5,"Quantity":60,"Discount":0.05}]}
{"OrderID":11013,"CustomerID":"ROMEY","OrderDate":"1998-04-09T00:00:00.000Z","LineItems":[{"ProductID":45,"UnitPrice":9.5,"Quantity":20,"Discount":0.0},{"ProductID":42,"UnitPrice":14.0,"Quantity":4,"Discount":0.0},{"ProductID":23,"UnitPrice":9.0,"Quantity":10,"Discount":0.0},{"ProductID":68,"UnitPrice":12.5,"Quantity":2,"Discount":0.0}]}
{"OrderID":11014,"CustomerID":"LINOD","OrderDate":"1998-04-10T00:00:00.000Z","LineItems":[{"ProductID":41,"UnitPrice":9.65,"Quantity":28,"Discount":0.1}]}
{"OrderID":11015,"CustomerID":"SANTG","OrderDate":"1998-04-10T00:00:00.000Z","LineItems":[{"ProductID":77,"UnitPrice":13.0,"Quantity":18,"Discount":0.0},{"ProductID":30,"UnitPrice":25.89,"Quantity":15,"Discount":0.0}]}
